cuizhanming_python_project1/__init__.py
cuizhanming_python_project1/cli.py
cuizhanming_python_project1/services.py
cuizhanming_python_project1-0.1.11.dist-info/METADATA
cuizhanming_python_project1-0.1.11.dist-info/WHEEL
cuizhanming_python_project1-0.1.11.dist-info/entry_points.txt
cuizhanming_python_project1-0.1.11.dist-info/RECORD
