Metadata-Version: 2.1
Name: cuizhanming-python-project1
Version: 0.1.11
Summary: 
Author: Z
Author-email: i@cui.guru
Requires-Python: >=3.13,<4.0
Classifier: Programming Language :: Python :: 3
Classifier: Programming Language :: Python :: 3.13
Requires-Dist: requests (>=2.32.3,<3.0.0)
